dtppy/__init__.py
dtppy/client.py
dtppy/crypto.py
dtppy/server.py
dtppy/util.py
dtppy-0.1.1.dist-info/METADATA
dtppy-0.1.1.dist-info/WHEEL
dtppy-0.1.1.dist-info/licenses/LICENSE
dtppy-0.1.1.dist-info/RECORD
