Metadata-Version: 2.1
Name: dtppy
Version: 0.1.1
Summary: Cross-platform networking interfaces for Python.
Project-URL: Homepage, https://wkhallen.com/dtp
Project-URL: Repository, https://github.com/WKHAllen/dtppy
Author-email: Will Allen <wkhallen@gmail.com>
License-Expression: MIT
License-File: LICENSE
Classifier: Intended Audience :: Developers
Classifier: License :: OSI Approved :: MIT License
Classifier: Operating System :: OS Independent
Classifier: Programming Language :: Python :: 3
Classifier: Programming Language :: Python :: 3.7
Classifier: Programming Language :: Python :: 3.8
Classifier: Programming Language :: Python :: 3.9
Classifier: Programming Language :: Python :: 3.10
Classifier: Programming Language :: Python :: 3.11
Classifier: Topic :: Software Development :: Libraries :: Application Frameworks
Classifier: Topic :: System :: Networking
Requires-Python: >=3.7
Requires-Dist: cryptography==37.0.4
Requires-Dist: rsa==4.9
